unoplat_code_confluence/__init__.py
unoplat_code_confluence/main.py
unoplat_code_confluence-0.2.1.dist-info/LICENSE
unoplat_code_confluence-0.2.1.dist-info/METADATA
unoplat_code_confluence-0.2.1.dist-info/WHEEL
unoplat_code_confluence-0.2.1.dist-info/entry_points.txt
unoplat_code_confluence-0.2.1.dist-info/RECORD
