Metadata-Version: 2.1
Name: unoplat-code-confluence
Version: 0.2.1
Summary: codebase understanding
Author: JayGhiya
Author-email: ghiya6548@gmail.com
Requires-Python: >=3.10,<=3.13
Classifier: Programming Language :: Python :: 3
Classifier: Programming Language :: Python :: 3.10
Classifier: Programming Language :: Python :: 3.11
Classifier: Programming Language :: Python :: 3.12
Requires-Dist: dspy-ai (>=2.4.9,<3.0.0)
Requires-Dist: litellm (>=1.37.19,<2.0.0)
Requires-Dist: loguru (>=0.7.2,<0.8.0)
Requires-Dist: marko (>=2.0.3,<3.0.0)
Requires-Dist: pydantic (>=2.7.1,<3.0.0)
Requires-Dist: pydantic-settings (>=2.2.1,<3.0.0)
Requires-Dist: pygithub (>=1.59.1,<2.0.0)
Requires-Dist: pypdf (>=3.11.0,<4.0.0)
Requires-Dist: pytest (>=8.2.1,<9.0.0)
Requires-Dist: ruff (>=0.4.4,<0.5.0)
